html_table_takeout/__init__.py
html_table_takeout/parser.py
html_table_takeout/py.typed
html_table_takeout/types.py
html_table_takeout-1.1.1.dist-info/licenses/LICENSE
html_table_takeout-1.1.1.dist-info/METADATA
html_table_takeout-1.1.1.dist-info/WHEEL
html_table_takeout-1.1.1.dist-info/top_level.txt
html_table_takeout-1.1.1.dist-info/RECORD
