Metadata-Version: 2.4
Name: html-table-takeout
Version: 1.1.1
Summary: HTML table parser that supports rowspan, colspan, links and nested tables. Fast, lightweight with no external dependencies.
Author: Calvin Law
Maintainer: Calvin Law
License: MIT
Project-URL: Homepage, https://github.com/lawcal/html-table-takeout
Keywords: html,table,parse,scrape
Classifier: Development Status :: 5 - Production/Stable
Classifier: Intended Audience :: Developers
Classifier: Topic :: Software Development :: Libraries :: Python Modules
Classifier: License :: OSI Approved :: MIT License
Classifier: Programming Language :: Python :: 3
Requires-Python: >=3.10
License-File: LICENSE
Dynamic: license-file
